auto_events
