Metadata-Version: 2.1
Name: auto-events
Version: 0.0.3
Summary: Automate tasks easily using python
Home-page: https://github.com/fedecech/auto_events
Author: Federico Cecchinato
Author-email: federicocech@gmail.com
License: MIT
Platform: UNKNOWN
Requires-Python: >=3.8
